balance_subscriber/__init__.py
balance_subscriber/__main__.py
balance_subscriber/client.py
balance_subscriber/exceptions.py
balance_subscriber/callbacks/__init__.py
balance_subscriber/callbacks/on_connect.py
balance_subscriber/callbacks/on_connect_fail.py
balance_subscriber/callbacks/on_message.py
balance_subscriber/callbacks/on_subscribe.py
balance_subscriber-1.0.1.dist-info/LICENSE
balance_subscriber-1.0.1.dist-info/METADATA
balance_subscriber-1.0.1.dist-info/WHEEL
balance_subscriber-1.0.1.dist-info/entry_points.txt
balance_subscriber-1.0.1.dist-info/top_level.txt
balance_subscriber-1.0.1.dist-info/RECORD
