Metadata-Version: 2.2
Name: balance-subscriber
Version: 1.0.1
Summary: MQTT listener to save data
Author-email: Joe Heffer <j.heffer@sheffield.ac.uk>
Project-URL: Homepage, https://pypi.org/p/balance-subscriber
Project-URL: Issues, https://github.com/IoT-balance-project/balance-mqtt-subscriber/issues
Classifier: Programming Language :: Python :: 3
Classifier: License :: OSI Approved :: MIT License
Classifier: Operating System :: OS Independent
Requires-Python: >=3.9
License-File: LICENSE
Requires-Dist: paho-mqtt==2.*
Provides-Extra: test
Requires-Dist: pytest==8.*; extra == "test"
Requires-Dist: flake8==7.*; extra == "test"
Requires-Dist: shellcheck-py==0.*; extra == "test"
